entropyguard/__init__.py
entropyguard/chunking/__init__.py
entropyguard/chunking/splitter.py
entropyguard/cli/__init__.py
entropyguard/cli/main.py
entropyguard/core/__init__.py
entropyguard/core/checkpoint.py
entropyguard/core/config_loader.py
entropyguard/core/config_validator.py
entropyguard/core/constants.py
entropyguard/core/error_messages.py
entropyguard/core/errors.py
entropyguard/core/exit_codes.py
entropyguard/core/logger.py
entropyguard/core/memory_profiler.py
entropyguard/core/metrics.py
entropyguard/core/pipeline.py
entropyguard/core/progress_tracker.py
entropyguard/core/resource_guards.py
entropyguard/core/retry.py
entropyguard/core/sanitization_lazy.py
entropyguard/core/types.py
entropyguard/deduplication/__init__.py
entropyguard/deduplication/embedder.py
entropyguard/deduplication/index.py
entropyguard/ingestion/__init__.py
entropyguard/ingestion/loader.py
entropyguard/ingestion/pdf_loader.py
entropyguard/sanitization/__init__.py
entropyguard/sanitization/core.py
entropyguard/validation/__init__.py
entropyguard/validation/validator.py
entropyguard-1.23.0.dist-info/entry_points.txt
entropyguard-1.23.0.dist-info/licenses/LICENSE
entropyguard-1.23.0.dist-info/METADATA
entropyguard-1.23.0.dist-info/WHEEL
entropyguard-1.23.0.dist-info/RECORD
