Metadata-Version: 2.4
Name: entropyguard
Version: 1.23.0
Summary: Enterprise-grade semantic data deduplication and sanitization engine.
License-File: LICENSE
Author: EntropyGuard Team
Requires-Python: >=3.10,<4.0
Classifier: Programming Language :: Python :: 3
Classifier: Programming Language :: Python :: 3.10
Classifier: Programming Language :: Python :: 3.11
Classifier: Programming Language :: Python :: 3.12
Classifier: Programming Language :: Python :: 3.13
Classifier: Programming Language :: Python :: 3.14
Provides-Extra: pdf
Requires-Dist: faiss-cpu (>=1.7.4,<2.0.0)
Requires-Dist: fastexcel (>=0.11.6,<0.12.0)
Requires-Dist: numpy (>=1.24.0,<2.0.0)
Requires-Dist: polars (>=0.20.0,<0.21.0)
Requires-Dist: pyarrow (>=15.0.0,<16.0.0)
Requires-Dist: pydantic (>=2.5.0,<3.0.0)
Requires-Dist: sentence-transformers (>=2.0.0,<3.0.0)
Requires-Dist: torch (>=2.1.0,<3.0.0)
Requires-Dist: typing-extensions (>=4.8.0,<5.0.0)
